VikScraper/Crawl.py
VikScraper/InfiniteCrawler.py
VikScraper/__init__.py
VikScraper-0.1.0.dist-info/METADATA
VikScraper-0.1.0.dist-info/WHEEL
VikScraper-0.1.0.dist-info/top_level.txt
VikScraper-0.1.0.dist-info/RECORD
